README.rst
setup.py
threadedprocess.py
threadedprocess.egg-info/PKG-INFO
threadedprocess.egg-info/SOURCES.txt
threadedprocess.egg-info/dependency_links.txt
threadedprocess.egg-info/requires.txt
threadedprocess.egg-info/top_level.txt