Metadata-Version: 1.1
Name: threadedprocess
Version: 0.0.3
Summary: A `ThreadedProcessPoolExecutor` is formed by a modified `ProcessPoolExecutor` that generates processes that use a `ThreadPoolExecutor` instance to run the given tasks.
Home-page: https://github.com/nilp0inter/threadedprocess
Author: Roberto Abdelkader Martinez Perez
Author-email: robertomartinezp@gmail.com
License: BSD
Keywords: concurrent futures executor process thread
Platform: UNKNOWN
Classifier: Development Status :: 3 - Alpha
Classifier: License :: OSI Approved :: BSD License
Classifier: Programming Language :: Python
Classifier: Programming Language :: Python :: 2
Classifier: Programming Language :: Python :: 2.6
Classifier: Programming Language :: Python :: 2.7
Classifier: Programming Language :: Python :: 3
Classifier: Programming Language :: Python :: 3.4
Classifier: Programming Language :: Python :: 3.5
Classifier: Programming Language :: Python :: 3.6
Classifier: Programming Language :: Python :: Implementation :: CPython
Classifier: Programming Language :: Python :: Implementation :: PyPy
